Workbook

Sheet Предложения
A1: № | B1: Источник | C1: Год | D1: Месяц вып. | E1: Модификация | F1: Пробег (км) | G1: Цвет кузова | H1: Цвет салона | I1: Состояние | J1: Битая | K1: FSD / Автопилот | L1: Город | M1: Цена (₽) | N1: Цена без НДС (₽) | O1: Продавец | P1: Происхождение | Q1: Контакт | R1: Ссылка | S1: Дата / статус | T1: Особые отметки | U1: Описание из объявления | V1: VIN | W1: Модельный год (VIN) | X1: Завод сборки (VIN) | Y1: VIN-проверка
A2: 1 | B2: Sravni.ru (лизинг) | C2: 2022 | D2: н/д | E2: LR AWD 450 л.с. | F2: 49355 | G2: чёрный | H2: н/д | I2: б/у среднее | J2: Неизв. | K2: Базовый | L2: Москва | M2: 5050000 | N2: =IF(OR(ISNUMBER(SEARCH("Физлицо",O2)),ISNUMBER(SEARCH("Частник",O2))),M2,M2/1.20) | O2: Лизинговая компания | P2: н/д | Q2: менеджер Sravni | R2: https://www.sravni.ru/biznes-leasing/technics/67f6b33dc60716c49d161770/ | S2: Активно | T2: ИЗЪЯТАЯ ТЕХНИКА | U2: Tesla Model Y AT, 2022 г.в., 49 355 км. Изъятая лизинговая техника. Чёрный, 450 л.с., AWD. Карточка лизингодателя на платформе Sravni.ru. | V2: — | W2: — | X2: — | Y2: — нет VIN для проверки
A3: 2 | B3: Telegram @TeslaRUShop | C3: 2021 | D3: Декабрь | E3: Long Range AWD | F3: 64000 | G3: н/д | H3: н/д | I3: б/у отличное | J3: Нет | K3: Базовый | L3: Москва | M3: 3800000 | N3: =IF(OR(ISNUMBER(SEARCH("Физлицо",O3)),ISNUMBER(SEARCH("Частник",O3))),M3,M3/1.20) | O3: Физлицо | P3: Германия | Q3: @Konstantin_Mankovskiy | R3: https://t.me/TeslaRUShop/4332 | S3: Активно | T3: ТО дек.2025: рычаги, сайленты, тепловой насос; **Несоответствие VIN ↔ заявленному происхождению**: VIN LRWYGCEK8MC128885 начинается с LRWY — это Giga Shanghai (Китай). Продавец заявляет Германию. | U3: Tesla Model Y Long Range AWD, декабрь 2021. Из Германии, 64 000 км. ТО декабрь 2025: заменены рычаги, сайленты. Тепловой насос. Без ДТП. Состояние отличное. | V3: LRWYGCEK8MC128885 | W3: 2021 | X3: Shanghai (Giga Shanghai), Китай | Y3: ✗ Завод не совпадает: заявлено «Германия», VIN = Китай | ✓ Год совпадает (2021)
A4: 3 | B4: Telegram @TeslaRUShop | C4: 2023 | D4: Июль | E4: Long Range Dual Motor | F4: 28100 | G4: серый металлик | H4: чёрный | I4: б/у отличное | J4: Нет | K4: Базовый | L4: Москва | M4: 4500000 | N4: =IF(OR(ISNUMBER(SEARCH("Физлицо",O4)),ISNUMBER(SEARCH("Частник",O4))),M4,M4/1.20) | O4: Физлицо (один владелец) | P4: Китай (Шанхай) | Q4: @chereshnevalina | R4: https://t.me/TeslaRUShop/4311 | S4: Активно | T4: EU-порты + GBT, подземная парковка | U4: Long Range Dual Motor из Шанхая, июль 2023, серый металлик. 28 100 км. EU-порты + GBT. Один владелец, подземная парковка, любые проверки приветствуются. | V4: LRWYGCEK9PC834851 | W4: 2023 | X4: Shanghai (Giga Shanghai), Китай | Y4: ✓ Завод совпадает (Китай) | ✓ Год совпадает (2023)
A5: 4 | B5: Telegram @TeslaRUShop | C5: 2023 | D5: Июнь | E5: Long Range (Giga Berlin) | F5: 44000 | G5: н/д | H5: н/д | I5: б/у отличное | J5: Нет | K5: Базовый | L5: Краснодар | M5: 4700000 | N5: =IF(OR(ISNUMBER(SEARCH("Физлицо",O5)),ISNUMBER(SEARCH("Частник",O5))),M5,M5/1.20) | O5: Физлицо | P5: Германия | Q5: @briisssk | R5: https://t.me/TeslaRUShop/4314 | S5: Активно | T5: CCS2, двойные стёкла, 2 компл. резины | U5: Long Range Giga Berlin июнь 2023, пробег 44 000 км. CCS2, двойные стёкла, тепловой насос, приложение работает, 2 комплекта резины. Без ДТП. | V5: XP7YGCEK2PB120211 | W5: 2023 | X5: Berlin (Giga Berlin), Германия | Y5: ✓ Завод совпадает (Германия) | ✓ Год совпадает (2023)
A6: 5 | B6: Telegram @TeslaRUShop | C6: 2021 | D6: Ноябрь (MY22) | E6: Long Range (US Copart) | F6: 31000 | G6: н/д | H6: н/д | I6: б/у, лёгкий биток | J6: Да (мин.) | K6: Базовый | L6: Санкт-Петербург | M6: 3900000 | N6: =IF(OR(ISNUMBER(SEARCH("Физлицо",O6)),ISNUMBER(SEARCH("Частник",O6))),M6,M6/1.20) | O6: Физлицо | P6: США | Q6: @maxniko90 | R6: https://t.me/TeslaRUShop/4320 | S6: Активно | T6: Бампер/крыло крашены, остальное родное, учёт РФ | U6: Long Range AWD, ноябрь 2021 (MY22), из США через Copart. Пробег 31 000 км. Бампер и крыло крашены после лёгкого ДТП, остальное родное. Учёт РФ. | V6: — | W6: — | X6: — | Y6: — нет VIN для проверки
A7: 6 | B7: Telegram @TeslaRUShop | C7: 2022 | D7: н/д | E7: Performance EU | F7: 22943 | G7: н/д | H7: н/д | I7: б/у отличное | J7: Нет | K7: Базовый | L7: Санкт-Петербург | M7: 5300000 | N7: =IF(OR(ISNUMBER(SEARCH("Физлицо",O7)),ISNUMBER(SEARCH("Частник",O7))),M7,M7/1.20) | O7: Физлицо | P7: EU | Q7: @andrey3128 | R7: https://t.me/TeslaRUShop/3978 | S7: Активно | T7: — | U7: Performance EU, 2022 г.в., пробег 22 943 км. Состояние отличное. Без ДТП. Берлинская сборка. | V7: XP7YGCEL8PB060041 | W7: 2023 | X7: Berlin (Giga Berlin), Германия | Y7: ⚠ Уточнение: заявлено «EU», VIN = Германия | ⚠ Год: заявлен 2022, MY2023 (норма ±1)
A8: 7 | B8: Telegram @TeslaRUShop | C8: 2022 | D8: Декабрь | E8: Performance (Berlin) | F8: 24800 | G8: белый перламутр | H8: чёрный | I8: б/у отличное | J8: Нет | K8: Базовый | L8: Москва | M8: 6000000 | N8: =IF(OR(ISNUMBER(SEARCH("Физлицо",O8)),ISNUMBER(SEARCH("Частник",O8))),M8,M8/1.20) | O8: Физлицо | P8: Берлин | Q8: — | R8: https://t.me/TeslaRUShop/4106 | S8: Активно | T8: Матричные фары, 393 кВт/534 л.с. | U8: Performance Berlin, декабрь 2022, белый перламутр на чёрном салоне. Пробег 24 800 км. Матричные фары, 393 кВт / 534 л.с., тепловой насос. | V8: — | W8: — | X8: — | Y8: — нет VIN для проверки
A9: 8 | B9: Telegram @TeslaRUShop | C9: 2023 | D9: н/д | E9: Performance | F9: 39000 | G9: н/д | H9: н/д | I9: б/у отличное | J9: Нет | K9: Базовый | L9: Москва | M9: 6300000 | N9: =IF(OR(ISNUMBER(SEARCH("Физлицо",O9)),ISNUMBER(SEARCH("Частник",O9))),M9,M9/1.20) | O9: Физлицо | P9: Германия | Q9: — | R9: https://t.me/TeslaRUShop/4085 | S9: Активно | T9: — | U9: Performance из Германии, 2023 г.в., 39 000 км. Состояние отличное. | V9: — | W9: — | X9: — | Y9: — нет VIN для проверки
A10: 9 | B10: Telegram @TeslaRUShop | C10: 2022 | D10: Декабрь | E10: Performance (Giga Berlin) | F10: 40500 | G10: н/д | H10: н/д | I10: б/у отличное | J10: Нет | K10: Базовый | L10: Москва | M10: 6390000 | N10: =IF(OR(ISNUMBER(SEARCH("Физлицо",O10)),ISNUMBER(SEARCH("Частник",O10))),M10,M10/1.20) | O10: Физлицо (в ПТС) | P10: Берлин | Q10: @Pavel_Ukolov | R10: https://t.me/s/teslarushop | S10: Активно | T10: Полностью в плёнке, R21 Uberturbine + R19 зима, BLE-сенсоры | U10: Performance Giga Berlin, декабрь 2022. Пробег 40 500 км. Полностью в плёнке, R21 Uberturbine + R19 зимняя резина, BLE-сенсоры. Один владелец в ПТС. | V10: — | W10: — | X10: — | Y10: — нет VIN для проверки
A11: 10 | B11: Telegram @TeslaRUShop | C11: 2023 | D11: н/д | E11: Performance | F11: 1000 | G11: н/д | H11: н/д | I11: Практически новый | J11: Нет | K11: Базовый | L11: Москва | M11: 7200000 | N11: =IF(OR(ISNUMBER(SEARCH("Физлицо",O11)),ISNUMBER(SEARCH("Частник",O11))),M11,M11/1.20) | O11: Физлицо/перекуп | P11: Китай | Q11: — | R11: https://t.me/TeslaRUShop/4026 | S11: Активно | T11: Фактически новый | U11: Performance 2023 из Китая, пробег 1 000 км. Фактически новый автомобиль. | V11: — | W11: — | X11: — | Y11: — нет VIN для проверки
A12: 11 | B12: Drom (зеркало Avito) | C12: 2022 | D12: н/д | E12: Long Range 75D | F12: 58000 | G12: н/д | H12: н/д | I12: б/у среднее | J12: Неизв. | K12: Базовый | L12: Москва | M12: 2850000 | N12: =IF(OR(ISNUMBER(SEARCH("Физлицо",O12)),ISNUMBER(SEARCH("Частник",O12))),M12,M12/1.20) | O12: Частник | P12: н/д | Q12: Drom | R12: https://auto.drom.ru/tesla/model_y/ | S12: Активно | T12: ВНИМАНИЕ: цена ниже рынка — требует проверки | U12: Long Range 75D, 2022 г.в., 58 000 км. Цена сильно ниже рынка — требует тщательной проверки документов и состояния. | V12: — | W12: — | X12: — | Y12: — нет VIN для проверки
A13: 12 | B13: Drom (зеркало Avito) | C13: 2022 | D13: н/д | E13: Long Range 75 kWh | F13: 19222 | G13: н/д | H13: н/д | I13: б/у отличное | J13: Неизв. | K13: Базовый | L13: Тюмень | M13: 4999000 | N13: =IF(OR(ISNUMBER(SEARCH("Физлицо",O13)),ISNUMBER(SEARCH("Частник",O13))),M13,M13/1.20) | O13: Автосалон FRESH | P13: н/д | Q13: Drom | R13: https://auto.drom.ru/tesla/model_y/ | S13: Активно | T13: Малый пробег, дилер | U13: Long Range 75 kWh, 2022 г.в., 19 222 км. Автосалон FRESH, Тюмень. Малый пробег, продажа от дилера. | V13: — | W13: — | X13: — | Y13: — нет VIN для проверки
... A123: 122 | B123: Avito (свежее, 21.05.2026) | C123: 2022 | D123: 01 | E123: Long Range 4WD AT (444 л.с.) | F123: 48000 | G123: чёрный | H123: Чёрный (Tesla базовый) | I123: Не битый, крашеных деталей нет | J123: Нет | K123: — | L123: Москва (2-й Мосфильмовский пер., р-н Поклонная/Минская) | M123: 4490000 | N123: =IF(OR(ISNUMBER(SEARCH("Физлицо",O123)),ISNUMBER(SEARCH("Частник",O123))),M123,M123/1.20) | O123: Физлицо (иван, на Авито с 2026) | P123: Германия (по словам продавца) — НО VIN LRWY указывает на Shanghai! | Q123: — | R123: https://www.avito.ru/moskva/avtomobili/tesla_model_y_at_2022_48_000_km_8079671471 | S123: Опубликовано: ~20.05.2026 (новое) | T123: **ТРЕТИЙ СЛУЧАЙ НЕСООТВЕТСТВИЯ**: продавец указывает «Европеец, привезен новым из Германии в январе 2023», но VIN LRWY*** однозначно указывает на Giga Shanghai (Китай). Передняя часть кузова, крылья, капот и бампер в плёнке. Пошиты индивидуальные ковры салона. Комплект зимней резины R20 + летней R21. В подарок новая оригинальная зарядка Wall Connector. Хранилась в подземном паркинге. ПТС электронный, 1 владелец. Продавец «иван» зарегистрирован в 2026 году — возможно новый аккаунт перекупа. Базовая комплектация, 444 л.с. | U123: Европеец, привезен новым из Германии в январе 2023. Без ДТП, крашенных деталей нет. Передняя часть кузова, крылья, капот и бампер в пленке. Пошиты индивидуальные ковры салона. Комплект зимней резины на оригинальных дисках R20. Комплект летней резины на оригинальных дисках R21. В подарок новая, оригинальная зарядка Wall Connector. Хранилась в подземном паркинге. | V123: LRWY*** (Giga Shanghai, Китай — НЕ Берлин!) | W123: ? (нет полного VIN) | X123: Shanghai (Giga Shanghai), Китай | Y123: ✗ Завод не совпадает: заявлено «Германия», VIN = Китай

Sheet Сводная статистика
A1: Tesla Model Y 2022+ AWD — Сводная статистика по российскому рынку
A2: Источники: Avito/Drom, Telegram @TeslaRUShop, лизинговые компании, дилерские каналы
A3: Дата обновления: 20 мая 2026
A5: 1. РАСПРЕДЕЛЕНИЕ ПО ИСТОЧНИКАМ
A6: Источник | B6: Кол-во | C6: Мин. цена (₽) | D6: Макс. цена (₽)
A7: Лизинг (изъятая) | B7: =COUNTIF(Предложения!B2:B123,"Sravni*") | C7: =SUMPRODUCT(MIN(IF(LEFT(Предложения!B2:B123,6)="Sravni",Предложения!M2:M123))) | D7: =SUMPRODUCT(MAX(IF(LEFT(Предложения!B2:B123,6)="Sravni",Предложения!M2:M123)))
A8: Telegram @TeslaRUShop | B8: =COUNTIF(Предложения!B2:B123,"Telegram*") | C8: =SUMPRODUCT(MIN(IF(LEFT(Предложения!B2:B123,8)="Telegram",Предложения!M2:M123))) | D8: =SUMPRODUCT(MAX(IF(LEFT(Предложения!B2:B123,8)="Telegram",Предложения!M2:M123)))
A9: Drom (зеркало Avito) | B9: =COUNTIF(Предложения!B2:B123,"Drom*") | C9: =SUMPRODUCT(MIN(IF(LEFT(Предложения!B2:B123,4)="Drom",Предложения!M2:M123))) | D9: =SUMPRODUCT(MAX(IF(LEFT(Предложения!B2:B123,4)="Drom",Предложения!M2:M123)))
A10: Дилерские каналы | B10: =COUNTIF(Предложения!B2:B123,"Дилер*") | C10: =SUMPRODUCT(MIN(IF(LEFT(Предложения!B2:B123,5)="Дилер",Предложения!M2:M123))) | D10: =SUMPRODUCT(MAX(IF(LEFT(Предложения!B2:B123,5)="Дилер",Предложения!M2:M123)))
A11: Avito | B11: =COUNTIF(Предложения!B2:B123,"Avito*") | C11: =SUMPRODUCT(MIN(IF(LEFT(Предложения!B2:B123,5)="Avito",Предложения!M2:M123))) | D11: =SUMPRODUCT(MAX(IF(LEFT(Предложения!B2:B123,5)="Avito",Предложения!M2:M123)))
A12: Auto.ru | B12: =COUNTIF(Предложения!B2:B123,"Auto.ru*") | C12: =SUMPRODUCT(MIN(IF(LEFT(Предложения!B2:B123,7)="Auto.ru",Предложения!M2:M123))) | D12: =SUMPRODUCT(MAX(IF(LEFT(Предложения!B2:B123,7)="Auto.ru",Предложения!M2:M123)))
A13: ВСЕГО | B13: =SUM(B7:B12) | C13: =MIN(Предложения!M2:M123) | D13: =MAX(Предложения!M2:M123)
A15: 2. РАСПРЕДЕЛЕНИЕ ПО ГОДАМ ВЫПУСКА
A16: Год выпуска | B16: Кол-во | C16: Средняя цена (₽) | D16: Мин. цена (₽)
A17: 2020 | B17: =COUNTIF(Предложения!C2:C123,2020) | C17: =IFERROR(AVERAGEIF(Предложения!C2:C123,2020,Предложения!M2:M123),"-") | D17: =SUMPRODUCT(MIN(IF(Предложения!C2:C123=2020,Предложения!M2:M123)))
A18: 2021 | B18: =COUNTIF(Предложения!C2:C123,2021) | C18: =IFERROR(AVERAGEIF(Предложения!C2:C123,2021,Предложения!M2:M123),"-") | D18: =SUMPRODUCT(MIN(IF(Предложения!C2:C123=2021,Предложения!M2:M123)))
A19: 2022 | B19: =COUNTIF(Предложения!C2:C123,2022) | C19: =IFERROR(AVERAGEIF(Предложения!C2:C123,2022,Предложения!M2:M123),"-") | D19: =SUMPRODUCT(MIN(IF(Предложения!C2:C123=2022,Предложения!M2:M123)))
A20: 2023 | B20: =COUNTIF(Предложения!C2:C123,2023) | C20: =IFERROR(AVERAGEIF(Предложения!C2:C123,2023,Предложения!M2:M123),"-") | D20: =SUMPRODUCT(MIN(IF(Предложения!C2:C123=2023,Предложения!M2:M123)))
A21: 2024 | B21: =COUNTIF(Предложения!C2:C123,2024) | C21: =IFERROR(AVERAGEIF(Предложения!C2:C123,2024,Предложения!M2:M123),"-") | D21: =SUMPRODUCT(MIN(IF(Предложения!C2:C123=2024,Предложения!M2:M123)))
A22: 2025 | B22: =COUNTIF(Предложения!C2:C123,2025) | C22: =IFERROR(AVERAGEIF(Предложения!C2:C123,2025,Предложения!M2:M123),"-") | D22: =SUMPRODUCT(MIN(IF(Предложения!C2:C123=2025,Предложения!M2:M123)))
A23: 3. РАСПРЕДЕЛЕНИЕ ПО ТИПУ ПРОДАВЦА
A24: Тип продавца | B24: Кол-во | C24: Средняя цена (₽) | D24: Доля (%)
A25: Физлицо | B25: =COUNTIF(Предложения!O2:O123,"Физлицо*")+COUNTIF(Предложения!O2:O123,"ИП*") | C25: =AVERAGEIF(Предложения!O2:O123,"Физлицо*",Предложения!M2:M123) | D25: =B25/COUNTA(Предложения!O2:O123)
A26: Юрлицо / Дилер | B26: =COUNTIF(Предложения!O2:O123,"Юрлицо*")+COUNTIF(Предложения!O2:O123,"Автосалон*") | C26: =AVERAGEIF(Предложения!O2:O123,"Юрлицо*",Предложения!M2:M123) | D26: =B26/COUNTA(Предложения!O2:O123)
A27: Частник / Прочее | B27: =COUNTA(Предложения!O2:O123)-B25-B26 | C27: =AVERAGEIF(Предложения!O2:O123,"Проверенный*",Предложения!M2:M123) | D27: =B27/COUNTA(Предложения!O2:O123)
A30: 4. ЦЕНОВЫЕ СЕГМЕНТЫ
A31: Сегмент | B31: Диапазон (₽) | C31: Кол-во | D31: Средн. пробег (км)
A32: Бюджетный | B32: до 4 500 000 | C32: =COUNTIFS(Предложения!M2:M123,"<=4500000") | D32: =AVERAGEIFS(Предложения!F2:F123,Предложения!M2:M123,"<=4500000")
A33: Средний | B33: 4 500 001 – 6 000 000 | C33: =COUNTIFS(Предложения!M2:M123,">4500000",Предложения!M2:M123,"<=6000000") | D33: =AVERAGEIFS(Предложения!F2:F123,Предложения!M2:M123,">4500000",Предложения!M2:M123,"<=6000000")
A34: Премиум б/у | B34: 6 000 001 – 7 500 000 | C34: =COUNTIFS(Предложения!M2:M123,">6000000",Предложения!M2:M123,"<=7500000") | D34: =AVERAGEIFS(Предложения!F2:F123,Предложения!M2:M123,">6000000",Предложения!M2:M123,"<=7500000")
A35: Новые / под заказ | B35: свыше 7 500 000 | C35: =COUNTIFS(Предложения!M2:M123,">7500000") | D35: =AVERAGEIFS(Предложения!F2:F123,Предложения!M2:M123,">7500000")
A38: 5. КЛЮЧЕВЫЕ ПОКАЗАТЕЛИ
A39: Самое дешёвое предложение (₽) | B39: =MIN(Предложения!M2:M123)
A40: Самое дорогое предложение (₽) | B40: =MAX(Предложения!M2:M123)
A41: Средняя цена по рынку (₽) | B41: =AVERAGE(Предложения!M2:M123)
A42: Медианная цена (₽) | B42: =MEDIAN(Предложения!M2:M123)
A43: Средний пробег б/у (км) | B43: =AVERAGEIF(Предложения!F2:F123,">0")
A44: Доля предложений без ДТП (%) | B44: =COUNTIF(Предложения!J2:J123,"Нет")/COUNTA(Предложения!J2:J123)
A45: Количество новых (пробег = 0) | B45: =COUNTIF(Предложения!F2:F123,0)
A46: Количество с пробегом | B46: =COUNTIF(Предложения!F2:F123,">0")

Sheet Примечания
A1: Tesla Model Y 2022+ AWD — Условные обозначения и важные примечания
A3: Дата отчёта | B3: 20 мая 2026
A4: Курс ЦБ РФ | B4: € = 82,7871 ₽ | $ = 71,2926 ₽
A6: ЦВЕТОВАЯ ИНДИКАЦИЯ СТРОК
A7: Жёлтый фон | B7: Изъятая лизинговая техника (особо интересная категория)
A8: Красный фон | B8: Подозрительно низкая цена — требует тщательной проверки
A9: Чередующиеся голубые/белые | B9: Обычные предложения
A11: РАСШИФРОВКА КОДОВ VIN (10-й символ = год модели)
A12: M | B12: Модельный год 2021
A13: N | B13: Модельный год 2022
A14: P | B14: Модельный год 2023
A15: R | B15: Модельный год 2024
A16: S | B16: Модельный год 2025
A18: ПЕРВЫЕ 3 СИМВОЛА VIN
A19: 5YJ или 7SA | B19: США (Fremont или Texas)
A20: XP7 | B20: Германия (Giga Berlin)
A21: LRW | B21: Китай (Giga Shanghai)
A23: ВАЖНЫЕ ПРИМЕЧАНИЯ
A24: Цена без НДС (₽) | B24: Колонка с автоматической формулой: если продавец содержит 'Физлицо' или 'Частник' — цена остаётся без изменений; для всех остальных (юрлица, дилеры, автосалоны, лизинговые компании) — цена делится на 1,22 (вычитается стандартная торговая наценка/НДС ~22%). Подсвечена светло-зелёным фоном
A25: Активные ссылки | B25: В колонке 'Ссылка' все URL кликабельны — нажмите на синий текст, чтобы перейти к объявлению
A26: Avito парсинг | B26: Прямой парсинг Avito заблокирован защитой сайта. Данные собраны через Drom.ru — крупнейший агрегатор-зеркало (объявления часто дублируются)
A27: Лизинговый сегмент | B27: Парк Tesla Model Y в корпоративном лизинге РФ ограничен (~1815 машин по данным АВТОСТАТ на 01.01.2025)
A28: Telegram | B28: Канал @TeslaRUShop (~3680 подписчиков) — главная барахолка по Tesla в РФ
A29: Утилизационный сбор | B29: С 01.01.2025 льготная ставка для физлиц при ввозе EV отменена: с 32 600 ₽ выросла до 667 400 ₽ (рост ~20x)
A30: Дилерские цены | B30: Moscow Tesla Club — 'под ключ' с растаможкой и ЭПТС. Electrodrivemoscow — цена в EU без таможни
A31: Рекомендация | B31: Лучшее соотношение цена/качество — Telegram-объявления от физлиц для машин 2022-2023 г.в. с пробегом 28-64 тыс. км из Берлина/Китая
A32: Описание из объявления | B32: Колонка U — оригинальные тексты описаний из карточек объявлений (Avito, Drom, Telegram @TeslaRUShop, Auto.ru). Для дилеров приведено описание из объявления; для частных объявлений — основной текст продавца. Полностью развёрнуть текст: ПКМ по ячейке → Высота строки → Авто.
A33: Новые объявления 21.05.2026 | B33: Строки 118–120 (подсвечены светло-зелёным) — это объявления Tesla Model Y AWD, опубликованные на Avito за последние 3 дня (18-21 мая 2026). Строка 118 — Ульяновск 2021 60т км 4,3 млн ₽ (продавец говорит Германия, но VIN LRWY указывает на Шанхай — несоответствие!). Строка 119 — Подольск 2022 68т км 4,0 млн ₽ AWD Performance USA. Строка 120 — Култаево 2020 65т км 4,0 млн ₽ Long Range Dual USA (вне фильтра 2022+, но AWD).
A34: Telegram-проверка 21.05.2026 | B34: Период: 21.02.2026 – 21.05.2026 (3 месяца). Проверены все доступные русскоязычные Tesla-каналы: - @TeslaRUShop (Купи/продай Тесла) — основной канал, 3.67K подписчиков. За 3 месяца 6 постов о Tesla Model Y: 2 уже в таблице (строки 4 и 5: LR Шанхай 28100 км и LR Berlin 44000 км), 3 — 2021 г.в. (вне фильтра), 1 — пост #Куплю (запрос покупателя). - @Moscow_Tesla_Club — маркетинговый канал автосалона, без объявлений. - @teslaclubrussia — пустой канал, 9 подписчиков. - @teslakupiprodai, @teslamarket, @teslarussia, @teslaperevozka, @teslamodely_chat — это пользовательские аккаунты, не каналы. - @tesla_msk — закрытая группа. - @teslacar_chat — общий чат, объявления делегируются в @TeslaRUShop. - @TeslaRUFix — про поломки. ИТОГ: новых уникальных объявлений Tesla Model Y AWD 2022+ за период 21.02-21.05.2026 в Telegram НЕ найдено.
A35: Обновление 21.05.2026 (Avito) | B35: Период проверки: 19-21 мая 2026 (2 дня). Проверены все источники: Avito + Drom + Auto.ru + Лизинг + Telegram. РЕЗУЛЬТАТ: • Avito — найдено 3 НОВЫХ уникальных объявления (строки 121-123, подсвечены светло-зелёным): #121 Тольятти 2023 LR Dual 29000 км 5,5М ₽ (США) — был ремонт ДТП #122 Москва Тропарёво 2022 Long Performance 40000 км 4,499М ₽ (Berlin) #123 Москва Мосфильмовский 2022 LR 4WD 48000 км 4,49М ₽ — **3-й случай несоответствия Германия↔Shanghai VIN!** • Drom — все 19-21 мая объявления уже в таблице (нет нового) • Auto.ru — недоступен (бот блокируется) • Лизинг (Sravni/Alfa/CARCADE) — без изменений • Telegram — без новых постов после 04.05.2026

Sheet Проверка таблицы
A1: Сводный отчёт проверки таблицы Tesla_ModelY_AWD_2026-05-20
A3: Дата проверки: 21.05.2026
A5: № Excel | B5: Категория | C5: Серьёзность | D5: Описание проблемы | E5: Действие
A6: 3 | B6: VIN несоответствие | C6: 🔴 Критично | D6: VIN LRWYGCEK8MC128885 — Giga Shanghai, но продавец заявляет Германия | E6: Подсвечено в столбце Y. Проверять при покупке.
A7: 118 | B7: VIN несоответствие | C7: 🔴 Критично | D7: VIN LRWY*** — Giga Shanghai, но продавец заявляет «из Германии» | E7: Подсвечено в столбце Y. Подозрительно — задать вопрос продавцу.
A8: 3 | B8: Фильтр года | C8: 🟡 Информация | D8: Год 2021 (попал из Telegram TeslaRUShop как уникальное предложение) | E8: Оставлено в таблице — пограничный случай (рестайл MY22)
A9: 6 | B9: Фильтр года | C9: 🟡 Информация | D9: Год 2021 (Tesla из США Copart) | E9: Оставлено в таблице
A10: 22 | B10: Фильтр года | C10: 🟡 Информация | D10: Год 2021 (Performance из Новороссийска, Drom) | E10: Оставлено в таблице
A11: 62 | B11: Фильтр года | C11: 🟡 Информация | D11: Год 2021 (LR Dual СПб) | E11: Оставлено в таблице
A12: 63 | B12: Фильтр года | C12: 🟡 Информация | D12: Год 2020 (Performance USA, Великие Луки) | E12: Оставлено в таблице — пограничный случай
A13: 68 | B13: Фильтр года | C13: 🟡 Информация | D13: Год 2021 (LR AWD Германия, Сочи) | E13: Оставлено в таблице
A14: 74 | B14: Фильтр года | C14: 🟡 Информация | D14: Год 2021 (AWD Performance, Магнитогорск 7-местный) | E14: Оставлено в таблице
A15: 118 | B15: Фильтр года | C15: 🟡 Информация | D15: Год 2021 (Ульяновск Long Range AWD) | E15: Оставлено в таблице
A16: 120 | B16: Фильтр года | C16: 🟡 Информация | D16: Год 2020 (Култаево LR Dual) | E16: Оставлено в таблице — пограничный случай
A17: 44 | B17: Модификация исправлена | C17: 🟢 Исправлено | D17: Было «Long Range AWD», в описании: «настоящий Performance, не шитый Long Range» | E17: ✓ Изменено на «Performance»
... A28: 103 | B28: Цена ниже медианы | C28: 🟡 Информация | D28: Цена 2 764 000 ₽ — 50% от медианы 5 500 000 ₽ для 2024 Long Range | E28: Объяснение: Молодечно (Беларусь), без растаможки в РФ
A31: ИТОГО: | B31: Всего проверено: 122 объявления
B32: 🔴 Критичных проблем: 2 (VIN-несоответствия)
B33: 🟢 Исправлено: 8 (неверные модификации)
B34: 🟡 Информация: 13 (вне фильтра года: 9, низкая цена: 4)
